{
  "asof": "2026-07-20T04:09:29Z",
  "index": 52.05,
  "label": "NEUTRAL",
  "signals": [
    {
      "key": "gpu_availability",
      "weight": 0.35,
      "z": 0.733,
      "direction": "up",
      "detail": "H100-class offers 44 (+12.8% vs prior)"
    },
    {
      "key": "token_economics",
      "weight": 0.25,
      "z": 0.0,
      "direction": "flat",
      "detail": "frontier $/M completion 15.0 (latest)"
    },
    {
      "key": "memory",
      "weight": 0.25,
      "z": 0.0,
      "direction": "flat",
      "detail": "insufficient history"
    },
    {
      "key": "gpu_price",
      "weight": 0.15,
      "z": -0.616,
      "direction": "down",
      "detail": "H100-class median $/hr 2.05 (7d mean)"
    }
  ]
}
