{
  "asof": "2026-07-20T07:35:13Z",
  "gpus": {
    "H100 SXM": {
      "offers": 30,
      "total_gpus": 69,
      "median_dph": 2.0008,
      "p25_dph": 1.7356,
      "min_dph": 1.1889
    },
    "H100 NVL": {
      "offers": 6,
      "total_gpus": 8,
      "median_dph": 2.068,
      "p25_dph": 1.9889,
      "min_dph": 1.9878
    },
    "H200": {
      "offers": 11,
      "total_gpus": 25,
      "median_dph": 4.08,
      "p25_dph": 4.0735,
      "min_dph": 3.9483
    },
    "B200": {
      "offers": 12,
      "total_gpus": 44,
      "median_dph": 7.4388,
      "p25_dph": 6.8771,
      "min_dph": 5.6252
    },
    "A100 SXM4": {
      "offers": 58,
      "total_gpus": 154,
      "median_dph": 0.8948,
      "p25_dph": 0.7334,
      "min_dph": 0.4007
    },
    "RTX 4090": {
      "offers": 64,
      "total_gpus": 198,
      "median_dph": 0.3785,
      "p25_dph": 0.3336,
      "min_dph": 0.1344
    },
    "MI300X": {
      "offers": 0,
      "total_gpus": 0,
      "median_dph": null,
      "p25_dph": null,
      "min_dph": null
    }
  },
  "errors": []
}
